fakejuju/__init__.py
fakejuju/failures.py
fakejuju/fakejuju.py
fakejuju/fixture.py
fakejuju/testing.py
fakejuju/tests/__init__.py
fakejuju/tests/test___init__.py
fakejuju/tests/test_failures.py
fakejuju/tests/test_fakejuju.py
fakejuju-0.0.1.dev308.dist-info/DESCRIPTION.rst
fakejuju-0.0.1.dev308.dist-info/METADATA
fakejuju-0.0.1.dev308.dist-info/RECORD
fakejuju-0.0.1.dev308.dist-info/WHEEL
fakejuju-0.0.1.dev308.dist-info/metadata.json
fakejuju-0.0.1.dev308.dist-info/pbr.json
fakejuju-0.0.1.dev308.dist-info/top_level.txt
