Metadata-Version: 2.0
Name: fakejuju
Version: 0.0.1.dev308
Summary: Drive fake-juju from Python
Home-page: https://github.com/juju/fake-juju
Author: Canonical Landscape team
Author-email: juju@lists.ubuntu.com
License: LGPLv3
Platform: POSIX
Classifier: License :: OSI Approved :: GNU Lesser General Public License v3 (LGPLv3)
Classifier: Operating System :: POSIX
Classifier: Programming Language :: Python :: 2
Classifier: Programming Language :: Python :: 3
Requires-Dist: PyYAML
Requires-Dist: Twisted
Requires-Dist: fixtures
Requires-Dist: pbr
Requires-Dist: pymongo
Requires-Dist: requests
Requires-Dist: testtools
Requires-Dist: txfixtures
Requires-Dist: txjuju (>=0.9.0a2)
Provides-Extra: test
Requires-Dist: testtools; extra == 'test'
